pyearthtools/training/__init__.py
pyearthtools/training/commands.py
pyearthtools/training/dataindex.py
pyearthtools/training/logger.py
pyearthtools/training/manage.py
pyearthtools/training/data/__init__.py
pyearthtools/training/data/datamodule.py
pyearthtools/training/data/fileio.py
pyearthtools/training/data/default/__init__.py
pyearthtools/training/data/default/datamodule.py
pyearthtools/training/data/default/datasets.py
pyearthtools/training/data/lightning/__init__.py
pyearthtools/training/data/lightning/datamodule.py
pyearthtools/training/data/lightning/datasets.py
pyearthtools/training/modules/__init__.py
pyearthtools/training/modules/optim.py
pyearthtools/training/modules/loss/__init__.py
pyearthtools/training/modules/loss/centre_weighted.py
pyearthtools/training/modules/loss/component.py
pyearthtools/training/modules/loss/extremes.py
pyearthtools/training/modules/loss/rmse.py
pyearthtools/training/modules/loss/structure.py
pyearthtools/training/wrapper/__init__.py
pyearthtools/training/wrapper/onnx.py
pyearthtools/training/wrapper/train.py
pyearthtools/training/wrapper/utils.py
pyearthtools/training/wrapper/wrapper.py
pyearthtools/training/wrapper/lightning/__init__.py
pyearthtools/training/wrapper/lightning/predict.py
pyearthtools/training/wrapper/lightning/train.py
pyearthtools/training/wrapper/lightning/wrapper.py
pyearthtools/training/wrapper/predict/__init__.py
pyearthtools/training/wrapper/predict/coupled.py
pyearthtools/training/wrapper/predict/predict.py
pyearthtools/training/wrapper/predict/timeseries.py
pyearthtools_training-0.5.1.dist-info/METADATA
pyearthtools_training-0.5.1.dist-info/WHEEL
pyearthtools_training-0.5.1.dist-info/entry_points.txt
pyearthtools_training-0.5.1.dist-info/licenses/LICENSE
pyearthtools_training-0.5.1.dist-info/RECORD
